tirds/__init__.py
tirds/backup.py
tirds/download.py
tirds/log.py
tirds/main.py
tirds/upload.py
tirds-0.0.2.dist-info/DESCRIPTION.rst
tirds-0.0.2.dist-info/METADATA
tirds-0.0.2.dist-info/RECORD
tirds-0.0.2.dist-info/WHEEL
tirds-0.0.2.dist-info/entry_points.txt
tirds-0.0.2.dist-info/metadata.json
tirds-0.0.2.dist-info/top_level.txt
