Metadata-Version: 2.0
Name: tirds
Version: 0.0.2
Summary: tirds is a command-line tool to backup and restore Google Cloud Datastore Entities via local
Home-page: https://github.com/drillbits/tirds
Author: drillbits
Author-email: neji@drillbits.jp
License: Apache 2.0
Keywords: appengine gae datastore backup restore
Platform: UNKNOWN
Classifier: Development Status :: 3 - Alpha
Classifier: Intended Audience :: Developers
Classifier: Topic :: System :: Archiving :: Backup
Classifier: License :: OSI Approved :: Apache Software License
Classifier: Programming Language :: Python :: 2.7
Classifier: Programming Language :: Python :: 2 :: Only
Requires-Dist: appengine-sdk
Requires-Dist: google-cloud-storage
Requires-Dist: pyyaml
